{
    "code": 0,
    "message": "success",
    "result": {
        "activity": {
            "head_bg_url": "",
            "id": 1537,
            "title": "补番月台第一期（2号站台）"
        },
        "alias": "",
        "areas": [
            {
                "id": 2,
                "name": "日本"
            }
        ],
        "bkg_cover": "",
        "cover": "http://i0.hdslb.com/bfs/bangumi/2b1aa93137e60ffc61d2376b9aba49def796149b.jpg",
        "episodes": [
            {
                "aid": 8374649,
                "badge": "",
                "badge_info": {
                    "bg_color": "#FB7299",
                    "bg_color_night": "#BB5B76",
                    "text": ""
                },
                "badge_type": 0,
                "bvid": "BV1qs41187Lq",
                "cid": 13784888,
                "cover": "http://i0.hdslb.com/bfs/bangumi/352c47c465482e7cb8c4cf1e6336309d12d2e5e7.jpg",
                "dimension": {
                    "height": 360,
                    "rotate": 0,
                    "width": 640
                },
                "duration": 1455000,
                "from": "bangumi",
                "id": 28202,
                "is_view_hide": false,
                "link": "https://www.bilibili.com/bangumi/play/ep28202",
                "long_title": "元气少女再结神",
                "pub_time": 1420484700,
                "pv": 0,
                "release_date": "",
                "rights": {
                    "allow_demand": 0,
                    "allow_dm": 1,
                    "allow_download": 1,
                    "area_limit": 0
                },
                "share_copy": "《元气少女缘结神◎》第1话 元气少女再结神",
                "share_url": "https://www.bilibili.com/bangumi/play/ep28202",
                "short_link": "https://b23.tv/ep28202",
                "skip": {
                    "ed": {
                        "end": 1430,
                        "start": 1363
                    },
                    "op": {
                        "end": 186,
                        "start": 97
                    }
                },
                "status": 2,
                "subtitle": "已观看5079.7万次",
                "title": "1",
                "vid": "vupload_13784888"
            },
            {
                "aid": 379321839,
                "badge": "",
                "badge_info": {
                    "bg_color": "#FB7299",
                    "bg_color_night": "#BB5B76",
                    "text": ""
                },
                "badge_type": 0,
                "bvid": "BV1bf4y1M7EF",
                "cid": 13784889,
                "cover": "http://i0.hdslb.com/bfs/bangumi/f10155a61187e7d8858a2331461ff440297a3b47.jpg",
                "dimension": {
                    "height": 360,
                    "rotate": 0,
                    "width": 640
                },
                "duration": 1456000,
                "from": "bangumi",
                "id": 28201,
                "is_view_hide": false,
                "link": "https://www.bilibili.com/bangumi/play/ep28201",
                "long_title": "神明，前往出云",
                "pub_time": 1421087702,
                "pv": 0,
                "release_date": "",
                "rights": {
                    "allow_demand": 0,
                    "allow_dm": 1,
                    "allow_download": 1,
                    "area_limit": 0
                },
                "share_copy": "《元气少女缘结神◎》第2话 神明，前往出云",
                "share_url": "https://www.bilibili.com/bangumi/play/ep28201",
                "short_link": "https://b23.tv/ep28201",
                "skip": {
                    "ed": {
                        "end": 1429,
                        "start": 1361
                    },
                    "op": {
                        "end": 114,
                        "start": 25
                    }
                },
                "status": 2,
                "subtitle": "已观看5079.7万次",
                "title": "2",
                "vid": "vupload_13784889"
            },
            {
                "aid": 676764705,
                "badge": "",
                "badge_info": {
                    "bg_color": "#FB7299",
                    "bg_color_night": "#BB5B76",
                    "text": ""
                },
                "badge_type": 0,
                "bvid": "BV1TU4y1u7cG",
                "cid": 13784890,
                "cover": "http://i0.hdslb.com/bfs/bangumi/f98ed13dc1b1b2cff097452b84e6716c4e221bfc.jpg",
                "dimension": {
                    "height": 360,
                    "rotate": 0,
                    "width": 640
                },
                "duration": 1455000,
                "from": "bangumi",
                "id": 28233,
                "is_view_hide": false,
                "link": "https://www.bilibili.com/bangumi/play/ep28233",
                "long_title": "神明，落入黄泉",
                "pub_time": 1422295503,
                "pv": 0,
                "release_date": "",
                "rights": {
                    "allow_demand": 0,
                    "allow_dm": 1,
                    "allow_download": 1,
                    "area_limit": 0
                },
                "share_copy": "《元气少女缘结神◎》第3话 神明，落入黄泉",
                "share_url": "https://www.bilibili.com/bangumi/play/ep28233",
                "short_link": "https://b23.tv/ep28233",
                "skip": {
                    "ed": {
                        "end": 1428,
                        "start": 1361
                    },
                    "op": {
                        "end": 110,
                        "start": 21
                    }
                },
                "status": 2,
                "subtitle": "已观看5079.7万次",
                "title": "3",
                "vid": "vupload_13784890"
            },
            {
                "aid": 294295952,
                "badge": "",
                "badge_info": {
                    "bg_color": "#FB7299",
                    "bg_color_night": "#BB5B76",
                    "text": ""
                },
                "badge_type": 0,
                "bvid": "BV1UF411h7MU",
                "cid": 13784891,
                "cover": "http://i0.hdslb.com/bfs/bangumi/042fc60986d0b2accdff5d9307ef3c2a888688e3.jpg",
                "dimension": {
                    "height": 360,
                    "rotate": 0,
                    "width": 640
                },
                "duration": 1456000,
                "from": "bangumi",
                "id": 28337,
                "is_view_hide": false,
                "link": "https://www.bilibili.com/bangumi/play/ep28337",
                "long_title": "神明，疾驰于黄泉",
                "pub_time": 1422900304,
                "pv": 0,
                "release_date": "",
                "rights": {
                    "allow_demand": 0,
                    "allow_dm": 1,
                    "allow_download": 1,
                    "area_limit": 0
                },
                "share_copy": "《元气少女缘结神◎》第4话 神明，疾驰于黄泉",
                "share_url": "https://www.bilibili.com/bangumi/play/ep28337",
                "short_link": "https://b23.tv/ep28337",
                "skip": {
                    "ed": {
                        "end": 1428,
                        "start": 1361
                    },
                    "op": {
                        "end": 116,
                        "start": 27
                    }
                },
                "status": 2,
                "subtitle": "已观看5079.7万次",
                "title": "4",
                "vid": "vupload_13784891"
            },
            {
                "aid": 934348549,
                "badge": "",
                "badge_info": {
                    "bg_color": "#FB7299",
                    "bg_color_night": "#BB5B76",
                    "text": ""
                },
                "badge_type": 0,
                "bvid": "BV1cM4y1P72M",
                "cid": 13784892,
                "cover": "http://i0.hdslb.com/bfs/bangumi/ac14d454a3af9b7f9574891cfdb8cfe75b3d3380.jpg",
                "dimension": {
                    "height": 360,
                    "rotate": 0,
                    "width": 640
                },
                "duration": 1457000,
                "from": "bangumi",
                "id": 28336,
                "is_view_hide": false,
                "link": "https://www.bilibili.com/bangumi/play/ep28336",
                "long_title": "神明，再一次告白",
                "pub_time": 1423505105,
                "pv": 0,
                "release_date": "",
                "rights": {
                    "allow_demand": 0,
                    "allow_dm": 1,
                    "allow_download": 1,
                    "area_limit": 0
                },
                "share_copy": "《元气少女缘结神◎》第5话 神明，再一次告白",
                "share_url": "https://www.bilibili.com/bangumi/play/ep28336",
                "short_link": "https://b23.tv/ep28336",
                "skip": {
                    "ed": {
                        "end": 1430,
                        "start": 1366
                    },
                    "op": {
                        "end": 90,
                        "start": 0
                    }
                },
                "status": 2,
                "subtitle": "已观看5079.7万次",
                "title": "5",
                "vid": "vupload_13784892"
            },
            {
                "aid": 591791675,
                "badge": "",
                "badge_info": {
                    "bg_color": "#FB7299",
                    "bg_color_night": "#BB5B76",
                    "text": ""
                },
                "badge_type": 0,
                "bvid": "BV1zq4y167MF",
                "cid": 13784893,
                "cover": "http://i0.hdslb.com/bfs/bangumi/ac84739f97f3ec7fd53d4f0c9a38c4d114ecfab6.jpg",
                "dimension": {
                    "height": 360,
                    "rotate": 0,
                    "width": 640
                },
                "duration": 1456000,
                "from": "bangumi",
                "id": 28387,
                "is_view_hide": false,
                "link": "https://www.bilibili.com/bangumi/play/ep28387",
                "long_title": "神明，遇见小天狗",
                "pub_time": 1424109906,
                "pv": 0,
                "release_date": "",
                "rights": {
                    "allow_demand": 0,
                    "allow_dm": 1,
                    "allow_download": 1,
                    "area_limit": 0
                },
                "share_copy": "《元气少女缘结神◎》第6话 神明，遇见小天狗",
                "share_url": "https://www.bilibili.com/bangumi/play/ep28387",
                "short_link": "https://b23.tv/ep28387",
                "skip": {
                    "ed": {
                        "end": 1428,
                        "start": 1365
                    },
                    "op": {
                        "end": 191,
                        "start": 102
                    }
                },
                "status": 2,
                "subtitle": "已观看5079.7万次",
                "title": "6",
                "vid": "vupload_13784893"
            },
            {
                "aid": 591780739,
                "badge": "",
                "badge_info": {
                    "bg_color": "#FB7299",
                    "bg_color_night": "#BB5B76",
                    "text": ""
                },
                "badge_type": 0,
                "bvid": "BV1sq4y167tv",
                "cid": 13784894,
                "cover": "http://i0.hdslb.com/bfs/bangumi/bb9d4cf263030f195f91e42d2d4ce65204f722f7.jpg",
                "dimension": {
                    "height": 360,
                    "rotate": 0,
                    "width": 640
                },
                "duration": 1456000,
                "from": "bangumi",
                "id": 28430,
                "is_view_hide": false,
                "link": "https://www.bilibili.com/bangumi/play/ep28430",
                "long_title": "神明，前往鞍马山",
                "pub_time": 1424714707,
                "pv": 0,
                "release_date": "",
                "rights": {
                    "allow_demand": 0,
                    "allow_dm": 1,
                    "allow_download": 1,
                    "area_limit": 0
                },
                "share_copy": "《元气少女缘结神◎》第7话 神明，前往鞍马山",
                "share_url": "https://www.bilibili.com/bangumi/play/ep28430",
                "short_link": "https://b23.tv/ep28430",
                "skip": {
                    "ed": {
                        "end": 1428,
                        "start": 1361
                    },
                    "op": {
                        "end": 105,
                        "start": 15
                    }
                },
                "status": 2,
                "subtitle": "已观看5079.7万次",
                "title": "7",
                "vid": "vupload_13784894"
            },
            {
                "aid": 934253108,
                "badge": "",
                "badge_info": {
                    "bg_color": "#FB7299",
                    "bg_color_night": "#BB5B76",
                    "text": ""
                },
                "badge_type": 0,
                "bvid": "BV1bT4y1R74A",
                "cid": 13784895,
                "cover": "http://i0.hdslb.com/bfs/bangumi/2d375c45f92819e8a5bce6763306c9317e7a1ca5.jpg",
                "dimension": {
                    "height": 360,
                    "rotate": 0,
                    "width": 640
                },
                "duration": 1456000,
                "from": "bangumi",
                "id": 28490,
                "is_view_hide": false,
                "link": "https://www.bilibili.com/bangumi/play/ep28490",
                "long_title": "神明，潜入",
                "pub_time": 1425319508,
                "pv": 0,
                "release_date": "",
                "rights": {
                    "allow_demand": 0,
                    "allow_dm": 1,
                    "allow_download": 1,
                    "area_limit": 0
                },
                "share_copy": "《元气少女缘结神◎》第8话 神明，潜入",
                "share_url": "https://www.bilibili.com/bangumi/play/ep28490",
                "short_link": "https://b23.tv/ep28490",
                "skip": {
                    "ed": {
                        "end": 1428,
                        "start": 1361
                    },
                    "op": {
                        "end": 128,
                        "start": 39
                    }
                },
                "status": 2,
                "subtitle": "已观看5079.7万次",
                "title": "8",
                "vid": "vupload_13784895"
            },
            {
                "aid": 336783197,
                "badge": "",
                "badge_info": {
                    "bg_color": "#FB7299",
                    "bg_color_night": "#BB5B76",
                    "text": ""
                },
                "badge_type": 0,
                "bvid": "BV1QR4y1t7wv",
                "cid": 13784896,
                "cover": "http://i0.hdslb.com/bfs/bangumi/17caaa908eda4e4bf1b75b79b2328b36ad0aa070.jpg",
                "dimension": {
                    "height": 360,
                    "rotate": 0,
                    "width": 640
                },
                "duration": 1455000,
                "from": "bangumi",
                "id": 28530,
                "is_view_hide": false,
                "link": "https://www.bilibili.com/bangumi/play/ep28530",
                "long_title": "神明，遭受突袭",
                "pub_time": 1425926109,
                "pv": 0,
                "release_date": "",
                "rights": {
                    "allow_demand": 0,
                    "allow_dm": 1,
                    "allow_download": 1,
                    "area_limit": 0
                },
                "share_copy": "《元气少女缘结神◎》第9话 神明，遭受突袭",
                "share_url": "https://www.bilibili.com/bangumi/play/ep28530",
                "short_link": "https://b23.tv/ep28530",
                "skip": {
                    "ed": {
                        "end": 1428,
                        "start": 1361
                    },
                    "op": {
                        "end": 124,
                        "start": 35
                    }
                },
                "status": 2,
                "subtitle": "已观看5079.7万次",
                "title": "9",
                "vid": "vupload_13784896"
            },
            {
                "aid": 806793803,
                "badge": "",
                "badge_info": {
                    "bg_color": "#FB7299",
                    "bg_color_night": "#BB5B76",
                    "text": ""
                },
                "badge_type": 0,
                "bvid": "BV1Z34y1d7aC",
                "cid": 13784897,
                "cover": "http://i0.hdslb.com/bfs/bangumi/828eff431ee8928a7222b890939da1940373433e.jpg",
                "dimension": {
                    "height": 360,
                    "rotate": 0,
                    "width": 640
                },
                "duration": 1455000,
                "from": "bangumi",
                "id": 28543,
                "is_view_hide": false,
                "link": "https://www.bilibili.com/bangumi/play/ep28543",
                "long_title": "神明，被告白",
                "pub_time": 1426530910,
                "pv": 0,
                "release_date": "",
                "rights": {
                    "allow_demand": 0,
                    "allow_dm": 1,
                    "allow_download": 1,
                    "area_limit": 0
                },
                "share_copy": "《元气少女缘结神◎》第10话 神明，被告白",
                "share_url": "https://www.bilibili.com/bangumi/play/ep28543",
                "short_link": "https://b23.tv/ep28543",
                "skip": {
                    "ed": {
                        "end": 0,
                        "start": 0
                    },
                    "op": {
                        "end": 104,
                        "start": 15
                    }
                },
                "status": 2,
                "subtitle": "已观看5079.7万次",
                "title": "10",
                "vid": "vupload_13784897"
            },
            {
                "aid": 209294752,
                "badge": "",
                "badge_info": {
                    "bg_color": "#FB7299",
                    "bg_color_night": "#BB5B76",
                    "text": ""
                },
                "badge_type": 0,
                "bvid": "BV1nh41147Co",
                "cid": 13784898,
                "cover": "http://i0.hdslb.com/bfs/bangumi/a9d3d8a2c53b07d3060ee6ce9017858fb46774dc.jpg",
                "dimension": {
                    "height": 360,
                    "rotate": 0,
                    "width": 640
                },
                "duration": 1457000,
                "from": "bangumi",
                "id": 28617,
                "is_view_hide": false,
                "link": "https://www.bilibili.com/bangumi/play/ep28617",
                "long_title": "神明，变回小孩",
                "pub_time": 1427135710,
                "pv": 0,
                "release_date": "",
                "rights": {
                    "allow_demand": 0,
                    "allow_dm": 1,
                    "allow_download": 1,
                    "area_limit": 0
                },
                "share_copy": "《元气少女缘结神◎》第11话 神明，变回小孩",
                "share_url": "https://www.bilibili.com/bangumi/play/ep28617",
                "short_link": "https://b23.tv/ep28617",
                "skip": {
                    "ed": {
                        "end": 1428,
                        "start": 1361
                    },
                    "op": {
                        "end": 146,
                        "start": 57
                    }
                },
                "status": 2,
                "subtitle": "已观看5079.7万次",
                "title": "11",
                "vid": "vupload_13784898"
            },
            {
                "aid": 591821706,
                "badge": "",
                "badge_info": {
                    "bg_color": "#FB7299",
                    "bg_color_night": "#BB5B76",
                    "text": ""
                },
                "badge_type": 0,
                "bvid": "BV1qq4y167B6",
                "cid": 13784899,
                "cover": "http://i0.hdslb.com/bfs/bangumi/96b8d176de9f448cf63adcae6bf9bde22bd4ef82.jpg",
                "dimension": {
                    "height": 360,
                    "rotate": 0,
                    "width": 640
                },
                "duration": 1440000,
                "from": "bangumi",
                "id": 28659,
                "is_view_hide": false,
                "link": "https://www.bilibili.com/bangumi/play/ep28659",
                "long_title": "神明，被求婚",
                "pub_time": 1427740512,
                "pv": 0,
                "release_date": "",
                "rights": {
                    "allow_demand": 0,
                    "allow_dm": 1,
                    "allow_download": 1,
                    "area_limit": 0
                },
                "share_copy": "《元气少女缘结神◎》第12话 神明，被求婚",
                "share_url": "https://www.bilibili.com/bangumi/play/ep28659",
                "short_link": "https://b23.tv/ep28659",
                "skip": {
                    "ed": {
                        "end": 1438,
                        "start": 1428
                    },
                    "op": {
                        "end": 104,
                        "start": 15
                    }
                },
                "status": 2,
                "subtitle": "已观看5079.7万次",
                "title": "12",
                "vid": "vupload_13784899"
            }
        ],
        "evaluate": "成为御影社土地神的是稚气未脱的女高中生·桃园奈奈生。某日，风神·乙比古带来了每年全国的神明们在出云集合召开的会议“神议”的请帖……",
        "freya": {
            "bubble_desc": "",
            "bubble_show_cnt": 0,
            "icon_show": 1
        },
        "jp_title": "",
        "link": "http://www.bilibili.com/bangumi/media/md1523/",
        "media_id": 1523,
        "mode": 2,
        "new_ep": {
            "desc": "已完结, 全12话",
            "id": 28659,
            "is_new": 0,
            "title": "12"
        },
        "positive": {
            "id": 18571,
            "title": "正片"
        },
        "publish": {
            "is_finish": 1,
            "is_started": 1,
            "pub_time": "2015-01-05 00:00:00",
            "pub_time_show": "2015年01月05日00:00",
            "unknow_pub_date": 0,
            "weekday": 0
        },
        "rating": {
            "count": 8889,
            "score": 9.7
        },
        "record": "",
        "rights": {
            "allow_bp": 1,
            "allow_bp_rank": 0,
            "allow_download": 0,
            "allow_review": 1,
            "area_limit": 317,
            "ban_area_show": 1,
            "can_watch": 1,
            "copyright": "bilibili",
            "forbid_pre": 0,
            "freya_white": 0,
            "is_cover_show": 0,
            "is_preview": 0,
            "only_vip_download": 0,
            "resource": "",
            "watch_platform": 0
        },
        "season_id": 1523,
        "season_title": "元气少女缘结神◎",
        "seasons": [
            {
                "badge": "",
                "badge_info": {
                    "bg_color": "#FB7299",
                    "bg_color_night": "#BB5B76",
                    "text": ""
                },
                "badge_type": 0,
                "cover": "http://i0.hdslb.com/bfs/bangumi/2b1aa93137e60ffc61d2376b9aba49def796149b.jpg",
                "horizontal_cover_1610": "",
                "horizontal_cover_169": "",
                "media_id": 1523,
                "new_ep": {
                    "cover": "http://i0.hdslb.com/bfs/bangumi/96b8d176de9f448cf63adcae6bf9bde22bd4ef82.jpg",
                    "id": 28659,
                    "index_show": "全12话"
                },
                "season_id": 1523,
                "season_title": "第二季",
                "season_type": 1,
                "stat": {
                    "favorites": 2897273,
                    "series_follow": 3140096,
                    "views": 50797194
                }
            },
            {
                "badge": "",
                "badge_info": {
                    "bg_color": "#FB7299",
                    "bg_color_night": "#BB5B76",
                    "text": ""
                },
                "badge_type": 0,
                "cover": "http://i0.hdslb.com/bfs/bangumi/177b0784b271b1bc517b9606adfc6ee6f1e430cf.jpg",
                "horizontal_cover_1610": "",
                "horizontal_cover_169": "",
                "media_id": 5882,
                "new_ep": {
                    "cover": "http://i2.hdslb.com/bfs/archive/5dab58bae29d2bd3c0330feef9fdf90d1b487ad8.jpg",
                    "id": 100722,
                    "index_show": "全1话"
                },
                "season_id": 5882,
                "season_title": "OVA",
                "season_type": 1,
                "stat": {
                    "favorites": 748218,
                    "series_follow": 3140096,
                    "views": 11720179
                }
            }
        ],
        "series": {
            "display_type": 0,
            "series_id": 1045,
            "series_title": "元气少女缘结神"
        },
        "share_copy": "《元气少女缘结神◎》美少女成为土地神",
        "share_sub_title": "美少女成为土地神",
        "share_url": "https://www.bilibili.com/bangumi/play/ss1523",
        "show": {
            "wide_screen": 0
        },
        "show_season_type": 1,
        "square_cover": "http://i0.hdslb.com/bfs/bangumi/b1a57e73d76ef60b644143255d3bb9a4a435a658.jpg",
        "stat": {
            "coins": 92918,
            "danmakus": 1367169,
            "favorite": 45314,
            "favorites": 2897273,
            "likes": 173896,
            "reply": 17322,
            "share": 40026,
            "views": 50797194
        },
        "status": 2,
        "subtitle": "已观看5079.7万次",
        "title": "元气少女缘结神◎",
        "total": 12,
        "type": 1,
        "user_status": {
            "area_limit": 0,
            "ban_area_show": 0,
            "follow": 0,
            "follow_status": 0,
            "login": 0,
            "pay": 0,
            "pay_pack_paid": 0,
            "sponsor": 0
        }
    }
}