{
    "code": 0,
    "message": "success",
    "result": {
        "activity": {
            "head_bg_url": "",
            "id": 0,
            "title": ""
        },
        "alias": "",
        "areas": [
            {
                "id": 2,
                "name": "日本"
            }
        ],
        "bkg_cover": "",
        "cover": "http://i0.hdslb.com/bfs/bangumi/3c8bae3be4814ad09a77e7dd79f4bd4d1e10a7cb.jpg",
        "episodes": [
            {
                "aid": 2976215,
                "badge": "",
                "badge_info": {
                    "bg_color": "#FB7299",
                    "bg_color_night": "#BB5B76",
                    "text": ""
                },
                "badge_type": 0,
                "bvid": "BV1os41117PM",
                "cid": 4662692,
                "cover": "http://i0.hdslb.com/bfs/bangumi/374a75794162ac9e1dee43d5b22700c94d37df79.jpg",
                "dimension": {
                    "height": 0,
                    "rotate": 0,
                    "width": 0
                },
                "duration": 1417272,
                "from": "bangumi",
                "id": 70712,
                "is_view_hide": false,
                "link": "https://www.bilibili.com/bangumi/play/ep70712",
                "long_title": "欢迎",
                "pub_time": 1443537120,
                "pv": 0,
                "release_date": "",
                "rights": {
                    "allow_demand": 0,
                    "allow_dm": 1,
                    "allow_download": 1,
                    "area_limit": 0
                },
                "share_copy": "《宇宙星路》第1话 欢迎",
                "share_url": "https://www.bilibili.com/bangumi/play/ep70712",
                "short_link": "https://b23.tv/ep70712",
                "skip": {
                    "ed": {
                        "end": 1385,
                        "start": 1314
                    },
                    "op": {
                        "end": 120,
                        "start": 30
                    }
                },
                "status": 2,
                "subtitle": "已观看23万次",
                "title": "1",
                "vid": "4175a4cab3"
            },
            {
                "aid": 2976215,
                "badge": "",
                "badge_info": {
                    "bg_color": "#FB7299",
                    "bg_color_night": "#BB5B76",
                    "text": ""
                },
                "badge_type": 0,
                "bvid": "BV1os41117PM",
                "cid": 4662693,
                "cover": "http://i0.hdslb.com/bfs/bangumi/374a75794162ac9e1dee43d5b22700c94d37df79.jpg",
                "dimension": {
                    "height": 0,
                    "rotate": 0,
                    "width": 0
                },
                "duration": 1417342,
                "from": "bangumi",
                "id": 70821,
                "is_view_hide": false,
                "link": "https://www.bilibili.com/bangumi/play/ep70821",
                "long_title": "迷失",
                "pub_time": 1443537120,
                "pv": 0,
                "release_date": "",
                "rights": {
                    "allow_demand": 0,
                    "allow_dm": 1,
                    "allow_download": 1,
                    "area_limit": 0
                },
                "share_copy": "《宇宙星路》第2话 迷失",
                "share_url": "https://www.bilibili.com/bangumi/play/ep70821",
                "short_link": "https://b23.tv/ep70821",
                "skip": {
                    "ed": {
                        "end": 1385,
                        "start": 1314
                    },
                    "op": {
                        "end": 120,
                        "start": 30
                    }
                },
                "status": 2,
                "subtitle": "已观看23万次",
                "title": "2",
                "vid": "5bc9951850"
            },
            {
                "aid": 2976215,
                "badge": "",
                "badge_info": {
                    "bg_color": "#FB7299",
                    "bg_color_night": "#BB5B76",
                    "text": ""
                },
                "badge_type": 0,
                "bvid": "BV1os41117PM",
                "cid": 4662694,
                "cover": "http://i0.hdslb.com/bfs/bangumi/374a75794162ac9e1dee43d5b22700c94d37df79.jpg",
                "dimension": {
                    "height": 0,
                    "rotate": 0,
                    "width": 0
                },
                "duration": 1417338,
                "from": "bangumi",
                "id": 70822,
                "is_view_hide": false,
                "link": "https://www.bilibili.com/bangumi/play/ep70822",
                "long_title": "对不起",
                "pub_time": 1443537120,
                "pv": 0,
                "release_date": "",
                "rights": {
                    "allow_demand": 0,
                    "allow_dm": 1,
                    "allow_download": 1,
                    "area_limit": 0
                },
                "share_copy": "《宇宙星路》第3话 对不起",
                "share_url": "https://www.bilibili.com/bangumi/play/ep70822",
                "short_link": "https://b23.tv/ep70822",
                "skip": {
                    "ed": {
                        "end": 1385,
                        "start": 1314
                    },
                    "op": {
                        "end": 120,
                        "start": 30
                    }
                },
                "status": 2,
                "subtitle": "已观看23万次",
                "title": "3",
                "vid": "ba9c891b93"
            },
            {
                "aid": 2976215,
                "badge": "",
                "badge_info": {
                    "bg_color": "#FB7299",
                    "bg_color_night": "#BB5B76",
                    "text": ""
                },
                "badge_type": 0,
                "bvid": "BV1os41117PM",
                "cid": 4662695,
                "cover": "http://i0.hdslb.com/bfs/bangumi/374a75794162ac9e1dee43d5b22700c94d37df79.jpg",
                "dimension": {
                    "height": 0,
                    "rotate": 0,
                    "width": 0
                },
                "duration": 1417279,
                "from": "bangumi",
                "id": 70798,
                "is_view_hide": false,
                "link": "https://www.bilibili.com/bangumi/play/ep70798",
                "long_title": "加油",
                "pub_time": 1443537120,
                "pv": 0,
                "release_date": "",
                "rights": {
                    "allow_demand": 0,
                    "allow_dm": 1,
                    "allow_download": 1,
                    "area_limit": 0
                },
                "share_copy": "《宇宙星路》第4话 加油",
                "share_url": "https://www.bilibili.com/bangumi/play/ep70798",
                "short_link": "https://b23.tv/ep70798",
                "skip": {
                    "ed": {
                        "end": 1385,
                        "start": 1314
                    },
                    "op": {
                        "end": 120,
                        "start": 30
                    }
                },
                "status": 2,
                "subtitle": "已观看23万次",
                "title": "4",
                "vid": "d4cb90fedc"
            },
            {
                "aid": 2976215,
                "badge": "",
                "badge_info": {
                    "bg_color": "#FB7299",
                    "bg_color_night": "#BB5B76",
                    "text": ""
                },
                "badge_type": 0,
                "bvid": "BV1os41117PM",
                "cid": 4662696,
                "cover": "http://i0.hdslb.com/bfs/bangumi/374a75794162ac9e1dee43d5b22700c94d37df79.jpg",
                "dimension": {
                    "height": 0,
                    "rotate": 0,
                    "width": 0
                },
                "duration": 1417488,
                "from": "bangumi",
                "id": 70824,
                "is_view_hide": false,
                "link": "https://www.bilibili.com/bangumi/play/ep70824",
                "long_title": "机会",
                "pub_time": 1443537120,
                "pv": 0,
                "release_date": "",
                "rights": {
                    "allow_demand": 0,
                    "allow_dm": 1,
                    "allow_download": 1,
                    "area_limit": 0
                },
                "share_copy": "《宇宙星路》第5话 机会",
                "share_url": "https://www.bilibili.com/bangumi/play/ep70824",
                "short_link": "https://b23.tv/ep70824",
                "skip": {
                    "ed": {
                        "end": 1385,
                        "start": 1314
                    },
                    "op": {
                        "end": 120,
                        "start": 30
                    }
                },
                "status": 2,
                "subtitle": "已观看23万次",
                "title": "5",
                "vid": "cd7907d992"
            },
            {
                "aid": 2976215,
                "badge": "",
                "badge_info": {
                    "bg_color": "#FB7299",
                    "bg_color_night": "#BB5B76",
                    "text": ""
                },
                "badge_type": 0,
                "bvid": "BV1os41117PM",
                "cid": 4662697,
                "cover": "http://i0.hdslb.com/bfs/bangumi/374a75794162ac9e1dee43d5b22700c94d37df79.jpg",
                "dimension": {
                    "height": 0,
                    "rotate": 0,
                    "width": 0
                },
                "duration": 1417478,
                "from": "bangumi",
                "id": 70825,
                "is_view_hide": false,
                "link": "https://www.bilibili.com/bangumi/play/ep70825",
                "long_title": "不会输的",
                "pub_time": 1443537120,
                "pv": 0,
                "release_date": "",
                "rights": {
                    "allow_demand": 0,
                    "allow_dm": 1,
                    "allow_download": 1,
                    "area_limit": 0
                },
                "share_copy": "《宇宙星路》第6话 不会输的",
                "share_url": "https://www.bilibili.com/bangumi/play/ep70825",
                "short_link": "https://b23.tv/ep70825",
                "skip": {
                    "ed": {
                        "end": 1385,
                        "start": 1314
                    },
                    "op": {
                        "end": 120,
                        "start": 30
                    }
                },
                "status": 2,
                "subtitle": "已观看23万次",
                "title": "6",
                "vid": "eedd9ee549"
            },
            {
                "aid": 2976215,
                "badge": "",
                "badge_info": {
                    "bg_color": "#FB7299",
                    "bg_color_night": "#BB5B76",
                    "text": ""
                },
                "badge_type": 0,
                "bvid": "BV1os41117PM",
                "cid": 4662698,
                "cover": "http://i0.hdslb.com/bfs/bangumi/374a75794162ac9e1dee43d5b22700c94d37df79.jpg",
                "dimension": {
                    "height": 0,
                    "rotate": 0,
                    "width": 0
                },
                "duration": 1416441,
                "from": "bangumi",
                "id": 70826,
                "is_view_hide": false,
                "link": "https://www.bilibili.com/bangumi/play/ep70826",
                "long_title": "不甘心",
                "pub_time": 1443537120,
                "pv": 0,
                "release_date": "",
                "rights": {
                    "allow_demand": 0,
                    "allow_dm": 1,
                    "allow_download": 1,
                    "area_limit": 0
                },
                "share_copy": "《宇宙星路》第7话 不甘心",
                "share_url": "https://www.bilibili.com/bangumi/play/ep70826",
                "short_link": "https://b23.tv/ep70826",
                "skip": {
                    "ed": {
                        "end": 1385,
                        "start": 1314
                    },
                    "op": {
                        "end": 120,
                        "start": 30
                    }
                },
                "status": 2,
                "subtitle": "已观看23万次",
                "title": "7",
                "vid": "1282addd00"
            },
            {
                "aid": 2976215,
                "badge": "",
                "badge_info": {
                    "bg_color": "#FB7299",
                    "bg_color_night": "#BB5B76",
                    "text": ""
                },
                "badge_type": 0,
                "bvid": "BV1os41117PM",
                "cid": 4662699,
                "cover": "http://i0.hdslb.com/bfs/bangumi/374a75794162ac9e1dee43d5b22700c94d37df79.jpg",
                "dimension": {
                    "height": 0,
                    "rotate": 0,
                    "width": 0
                },
                "duration": 1417464,
                "from": "bangumi",
                "id": 70827,
                "is_view_hide": false,
                "link": "https://www.bilibili.com/bangumi/play/ep70827",
                "long_title": "是我吗？",
                "pub_time": 1443537120,
                "pv": 0,
                "release_date": "",
                "rights": {
                    "allow_demand": 0,
                    "allow_dm": 1,
                    "allow_download": 1,
                    "area_limit": 0
                },
                "share_copy": "《宇宙星路》第8话 是我吗？",
                "share_url": "https://www.bilibili.com/bangumi/play/ep70827",
                "short_link": "https://b23.tv/ep70827",
                "skip": {
                    "ed": {
                        "end": 1385,
                        "start": 1314
                    },
                    "op": {
                        "end": 120,
                        "start": 30
                    }
                },
                "status": 2,
                "subtitle": "已观看23万次",
                "title": "8",
                "vid": "b1adaec1a3"
            },
            {
                "aid": 2976215,
                "badge": "",
                "badge_info": {
                    "bg_color": "#FB7299",
                    "bg_color_night": "#BB5B76",
                    "text": ""
                },
                "badge_type": 0,
                "bvid": "BV1os41117PM",
                "cid": 4662700,
                "cover": "http://i0.hdslb.com/bfs/bangumi/374a75794162ac9e1dee43d5b22700c94d37df79.jpg",
                "dimension": {
                    "height": 0,
                    "rotate": 0,
                    "width": 0
                },
                "duration": 1417294,
                "from": "bangumi",
                "id": 70828,
                "is_view_hide": false,
                "link": "https://www.bilibili.com/bangumi/play/ep70828",
                "long_title": "我去了",
                "pub_time": 1443537120,
                "pv": 0,
                "release_date": "",
                "rights": {
                    "allow_demand": 0,
                    "allow_dm": 1,
                    "allow_download": 1,
                    "area_limit": 0
                },
                "share_copy": "《宇宙星路》第9话 我去了",
                "share_url": "https://www.bilibili.com/bangumi/play/ep70828",
                "short_link": "https://b23.tv/ep70828",
                "skip": {
                    "ed": {
                        "end": 1385,
                        "start": 1314
                    },
                    "op": {
                        "end": 120,
                        "start": 30
                    }
                },
                "status": 2,
                "subtitle": "已观看23万次",
                "title": "9",
                "vid": "2f287015b4"
            },
            {
                "aid": 2976215,
                "badge": "",
                "badge_info": {
                    "bg_color": "#FB7299",
                    "bg_color_night": "#BB5B76",
                    "text": ""
                },
                "badge_type": 0,
                "bvid": "BV1os41117PM",
                "cid": 4662701,
                "cover": "http://i0.hdslb.com/bfs/bangumi/374a75794162ac9e1dee43d5b22700c94d37df79.jpg",
                "dimension": {
                    "height": 0,
                    "rotate": 0,
                    "width": 0
                },
                "duration": 1417166,
                "from": "bangumi",
                "id": 70829,
                "is_view_hide": false,
                "link": "https://www.bilibili.com/bangumi/play/ep70829",
                "long_title": "欢迎回来",
                "pub_time": 1443537120,
                "pv": 0,
                "release_date": "",
                "rights": {
                    "allow_demand": 0,
                    "allow_dm": 1,
                    "allow_download": 1,
                    "area_limit": 0
                },
                "share_copy": "《宇宙星路》第10话 欢迎回来",
                "share_url": "https://www.bilibili.com/bangumi/play/ep70829",
                "short_link": "https://b23.tv/ep70829",
                "skip": {
                    "ed": {
                        "end": 1385,
                        "start": 1314
                    },
                    "op": {
                        "end": 120,
                        "start": 30
                    }
                },
                "status": 2,
                "subtitle": "已观看23万次",
                "title": "10",
                "vid": "df8d4de30c"
            },
            {
                "aid": 2976215,
                "badge": "",
                "badge_info": {
                    "bg_color": "#FB7299",
                    "bg_color_night": "#BB5B76",
                    "text": ""
                },
                "badge_type": 0,
                "bvid": "BV1os41117PM",
                "cid": 4662702,
                "cover": "http://i0.hdslb.com/bfs/bangumi/374a75794162ac9e1dee43d5b22700c94d37df79.jpg",
                "dimension": {
                    "height": 0,
                    "rotate": 0,
                    "width": 0
                },
                "duration": 1417333,
                "from": "bangumi",
                "id": 70830,
                "is_view_hide": false,
                "link": "https://www.bilibili.com/bangumi/play/ep70830",
                "long_title": "真正的你",
                "pub_time": 1443537120,
                "pv": 0,
                "release_date": "",
                "rights": {
                    "allow_demand": 0,
                    "allow_dm": 1,
                    "allow_download": 1,
                    "area_limit": 0
                },
                "share_copy": "《宇宙星路》第11话 真正的你",
                "share_url": "https://www.bilibili.com/bangumi/play/ep70830",
                "short_link": "https://b23.tv/ep70830",
                "skip": {
                    "ed": {
                        "end": 1385,
                        "start": 1314
                    },
                    "op": {
                        "end": 120,
                        "start": 30
                    }
                },
                "status": 2,
                "subtitle": "已观看23万次",
                "title": "11",
                "vid": "1cfd545c1b"
            },
            {
                "aid": 2976215,
                "badge": "",
                "badge_info": {
                    "bg_color": "#FB7299",
                    "bg_color_night": "#BB5B76",
                    "text": ""
                },
                "badge_type": 0,
                "bvid": "BV1os41117PM",
                "cid": 4662703,
                "cover": "http://i0.hdslb.com/bfs/bangumi/374a75794162ac9e1dee43d5b22700c94d37df79.jpg",
                "dimension": {
                    "height": 0,
                    "rotate": 0,
                    "width": 0
                },
                "duration": 1417285,
                "from": "bangumi",
                "id": 70831,
                "is_view_hide": false,
                "link": "https://www.bilibili.com/bangumi/play/ep70831",
                "long_title": "告白",
                "pub_time": 1443537120,
                "pv": 0,
                "release_date": "",
                "rights": {
                    "allow_demand": 0,
                    "allow_dm": 1,
                    "allow_download": 1,
                    "area_limit": 0
                },
                "share_copy": "《宇宙星路》第12话 告白",
                "share_url": "https://www.bilibili.com/bangumi/play/ep70831",
                "short_link": "https://b23.tv/ep70831",
                "skip": {
                    "ed": {
                        "end": 1385,
                        "start": 1314
                    },
                    "op": {
                        "end": 120,
                        "start": 30
                    }
                },
                "status": 2,
                "subtitle": "已观看23万次",
                "title": "12",
                "vid": "168aa1528a"
            },
            {
                "aid": 2976215,
                "badge": "",
                "badge_info": {
                    "bg_color": "#FB7299",
                    "bg_color_night": "#BB5B76",
                    "text": ""
                },
                "badge_type": 0,
                "bvid": "BV1os41117PM",
                "cid": 4662704,
                "cover": "http://i0.hdslb.com/bfs/bangumi/374a75794162ac9e1dee43d5b22700c94d37df79.jpg",
                "dimension": {
                    "height": 0,
                    "rotate": 0,
                    "width": 0
                },
                "duration": 1417441,
                "from": "bangumi",
                "id": 70807,
                "is_view_hide": false,
                "link": "https://www.bilibili.com/bangumi/play/ep70807",
                "long_title": "寒假",
                "pub_time": 1443537120,
                "pv": 0,
                "release_date": "",
                "rights": {
                    "allow_demand": 0,
                    "allow_dm": 1,
                    "allow_download": 1,
                    "area_limit": 0
                },
                "share_copy": "《宇宙星路》第13话 寒假",
                "share_url": "https://www.bilibili.com/bangumi/play/ep70807",
                "short_link": "https://b23.tv/ep70807",
                "skip": {
                    "ed": {
                        "end": 1385,
                        "start": 1314
                    },
                    "op": {
                        "end": 120,
                        "start": 30
                    }
                },
                "status": 2,
                "subtitle": "已观看23万次",
                "title": "13",
                "vid": "18eaafabc6"
            },
            {
                "aid": 2976215,
                "badge": "",
                "badge_info": {
                    "bg_color": "#FB7299",
                    "bg_color_night": "#BB5B76",
                    "text": ""
                },
                "badge_type": 0,
                "bvid": "BV1os41117PM",
                "cid": 4662705,
                "cover": "http://i0.hdslb.com/bfs/bangumi/374a75794162ac9e1dee43d5b22700c94d37df79.jpg",
                "dimension": {
                    "height": 0,
                    "rotate": 0,
                    "width": 0
                },
                "duration": 1417323,
                "from": "bangumi",
                "id": 70833,
                "is_view_hide": false,
                "link": "https://www.bilibili.com/bangumi/play/ep70833",
                "long_title": "梦和现实",
                "pub_time": 1443537120,
                "pv": 0,
                "release_date": "",
                "rights": {
                    "allow_demand": 0,
                    "allow_dm": 1,
                    "allow_download": 1,
                    "area_limit": 0
                },
                "share_copy": "《宇宙星路》第14话 梦和现实",
                "share_url": "https://www.bilibili.com/bangumi/play/ep70833",
                "short_link": "https://b23.tv/ep70833",
                "skip": {
                    "ed": {
                        "end": 1385,
                        "start": 1314
                    },
                    "op": {
                        "end": 120,
                        "start": 30
                    }
                },
                "status": 2,
                "subtitle": "已观看23万次",
                "title": "14",
                "vid": "c66d559d34"
            },
            {
                "aid": 2976215,
                "badge": "",
                "badge_info": {
                    "bg_color": "#FB7299",
                    "bg_color_night": "#BB5B76",
                    "text": ""
                },
                "badge_type": 0,
                "bvid": "BV1os41117PM",
                "cid": 4662706,
                "cover": "http://i0.hdslb.com/bfs/bangumi/374a75794162ac9e1dee43d5b22700c94d37df79.jpg",
                "dimension": {
                    "height": 0,
                    "rotate": 0,
                    "width": 0
                },
                "duration": 1417294,
                "from": "bangumi",
                "id": 70834,
                "is_view_hide": false,
                "link": "https://www.bilibili.com/bangumi/play/ep70834",
                "long_title": "我不知道",
                "pub_time": 1443537120,
                "pv": 0,
                "release_date": "",
                "rights": {
                    "allow_demand": 0,
                    "allow_dm": 1,
                    "allow_download": 1,
                    "area_limit": 0
                },
                "share_copy": "《宇宙星路》第15话 我不知道",
                "share_url": "https://www.bilibili.com/bangumi/play/ep70834",
                "short_link": "https://b23.tv/ep70834",
                "skip": {
                    "ed": {
                        "end": 1385,
                        "start": 1314
                    },
                    "op": {
                        "end": 120,
                        "start": 30
                    }
                },
                "status": 2,
                "subtitle": "已观看23万次",
                "title": "15",
                "vid": "9b358ad243"
            },
            {
                "aid": 2976215,
                "badge": "",
                "badge_info": {
                    "bg_color": "#FB7299",
                    "bg_color_night": "#BB5B76",
                    "text": ""
                },
                "badge_type": 0,
                "bvid": "BV1os41117PM",
                "cid": 4662707,
                "cover": "http://i0.hdslb.com/bfs/bangumi/374a75794162ac9e1dee43d5b22700c94d37df79.jpg",
                "dimension": {
                    "height": 0,
                    "rotate": 0,
                    "width": 0
                },
                "duration": 1417280,
                "from": "bangumi",
                "id": 70835,
                "is_view_hide": false,
                "link": "https://www.bilibili.com/bangumi/play/ep70835",
                "long_title": "在怀疑中",
                "pub_time": 1443537120,
                "pv": 0,
                "release_date": "",
                "rights": {
                    "allow_demand": 0,
                    "allow_dm": 1,
                    "allow_download": 1,
                    "area_limit": 0
                },
                "share_copy": "《宇宙星路》第16话 在怀疑中",
                "share_url": "https://www.bilibili.com/bangumi/play/ep70835",
                "short_link": "https://b23.tv/ep70835",
                "skip": {
                    "ed": {
                        "end": 1385,
                        "start": 1314
                    },
                    "op": {
                        "end": 120,
                        "start": 30
                    }
                },
                "status": 2,
                "subtitle": "已观看23万次",
                "title": "16",
                "vid": "3c3f339266"
            },
            {
                "aid": 2976215,
                "badge": "",
                "badge_info": {
                    "bg_color": "#FB7299",
                    "bg_color_night": "#BB5B76",
                    "text": ""
                },
                "badge_type": 0,
                "bvid": "BV1os41117PM",
                "cid": 4662708,
                "cover": "http://i0.hdslb.com/bfs/bangumi/374a75794162ac9e1dee43d5b22700c94d37df79.jpg",
                "dimension": {
                    "height": 0,
                    "rotate": 0,
                    "width": 0
                },
                "duration": 1417001,
                "from": "bangumi",
                "id": 70784,
                "is_view_hide": false,
                "link": "https://www.bilibili.com/bangumi/play/ep70784",
                "long_title": "战斗",
                "pub_time": 1443537120,
                "pv": 0,
                "release_date": "",
                "rights": {
                    "allow_demand": 0,
                    "allow_dm": 1,
                    "allow_download": 1,
                    "area_limit": 0
                },
                "share_copy": "《宇宙星路》第17话 战斗",
                "share_url": "https://www.bilibili.com/bangumi/play/ep70784",
                "short_link": "https://b23.tv/ep70784",
                "skip": {
                    "ed": {
                        "end": 1385,
                        "start": 1314
                    },
                    "op": {
                        "end": 120,
                        "start": 30
                    }
                },
                "status": 2,
                "subtitle": "已观看23万次",
                "title": "17",
                "vid": "fbdf5f26d6"
            },
            {
                "aid": 2976215,
                "badge": "",
                "badge_info": {
                    "bg_color": "#FB7299",
                    "bg_color_night": "#BB5B76",
                    "text": ""
                },
                "badge_type": 0,
                "bvid": "BV1os41117PM",
                "cid": 4662709,
                "cover": "http://i0.hdslb.com/bfs/bangumi/374a75794162ac9e1dee43d5b22700c94d37df79.jpg",
                "dimension": {
                    "height": 0,
                    "rotate": 0,
                    "width": 0
                },
                "duration": 1417426,
                "from": "bangumi",
                "id": 70785,
                "is_view_hide": false,
                "link": "https://www.bilibili.com/bangumi/play/ep70785",
                "long_title": "遥远的声音",
                "pub_time": 1443537120,
                "pv": 0,
                "release_date": "",
                "rights": {
                    "allow_demand": 0,
                    "allow_dm": 1,
                    "allow_download": 1,
                    "area_limit": 0
                },
                "share_copy": "《宇宙星路》第18话 遥远的声音",
                "share_url": "https://www.bilibili.com/bangumi/play/ep70785",
                "short_link": "https://b23.tv/ep70785",
                "skip": {
                    "ed": {
                        "end": 1385,
                        "start": 1314
                    },
                    "op": {
                        "end": 120,
                        "start": 30
                    }
                },
                "status": 2,
                "subtitle": "已观看23万次",
                "title": "18",
                "vid": "19086de413"
            },
            {
                "aid": 2976215,
                "badge": "",
                "badge_info": {
                    "bg_color": "#FB7299",
                    "bg_color_night": "#BB5B76",
                    "text": ""
                },
                "badge_type": 0,
                "bvid": "BV1os41117PM",
                "cid": 4662710,
                "cover": "http://i0.hdslb.com/bfs/bangumi/374a75794162ac9e1dee43d5b22700c94d37df79.jpg",
                "dimension": {
                    "height": 0,
                    "rotate": 0,
                    "width": 0
                },
                "duration": 1417297,
                "from": "bangumi",
                "id": 70838,
                "is_view_hide": false,
                "link": "https://www.bilibili.com/bangumi/play/ep70838",
                "long_title": "胆小鬼 急性子",
                "pub_time": 1443537120,
                "pv": 0,
                "release_date": "",
                "rights": {
                    "allow_demand": 0,
                    "allow_dm": 1,
                    "allow_download": 1,
                    "area_limit": 0
                },
                "share_copy": "《宇宙星路》第19话 胆小鬼 急性子",
                "share_url": "https://www.bilibili.com/bangumi/play/ep70838",
                "short_link": "https://b23.tv/ep70838",
                "skip": {
                    "ed": {
                        "end": 1385,
                        "start": 1314
                    },
                    "op": {
                        "end": 120,
                        "start": 30
                    }
                },
                "status": 2,
                "subtitle": "已观看23万次",
                "title": "19",
                "vid": "76bef09192"
            },
            {
                "aid": 2976215,
                "badge": "",
                "badge_info": {
                    "bg_color": "#FB7299",
                    "bg_color_night": "#BB5B76",
                    "text": ""
                },
                "badge_type": 0,
                "bvid": "BV1os41117PM",
                "cid": 4662711,
                "cover": "http://i0.hdslb.com/bfs/bangumi/374a75794162ac9e1dee43d5b22700c94d37df79.jpg",
                "dimension": {
                    "height": 0,
                    "rotate": 0,
                    "width": 0
                },
                "duration": 1416446,
                "from": "bangumi",
                "id": 70839,
                "is_view_hide": false,
                "link": "https://www.bilibili.com/bangumi/play/ep70839",
                "long_title": "给予你未来",
                "pub_time": 1443537120,
                "pv": 0,
                "release_date": "",
                "rights": {
                    "allow_demand": 0,
                    "allow_dm": 1,
                    "allow_download": 1,
                    "area_limit": 0
                },
                "share_copy": "《宇宙星路》第20话 给予你未来",
                "share_url": "https://www.bilibili.com/bangumi/play/ep70839",
                "short_link": "https://b23.tv/ep70839",
                "skip": {
                    "ed": {
                        "end": 1385,
                        "start": 1314
                    },
                    "op": {
                        "end": 120,
                        "start": 30
                    }
                },
                "status": 2,
                "subtitle": "已观看23万次",
                "title": "20",
                "vid": "cda221a2ad"
            },
            {
                "aid": 2976215,
                "badge": "",
                "badge_info": {
                    "bg_color": "#FB7299",
                    "bg_color_night": "#BB5B76",
                    "text": ""
                },
                "badge_type": 0,
                "bvid": "BV1os41117PM",
                "cid": 4662712,
                "cover": "http://i0.hdslb.com/bfs/bangumi/374a75794162ac9e1dee43d5b22700c94d37df79.jpg",
                "dimension": {
                    "height": 0,
                    "rotate": 0,
                    "width": 0
                },
                "duration": 1417518,
                "from": "bangumi",
                "id": 70840,
                "is_view_hide": false,
                "link": "https://www.bilibili.com/bangumi/play/ep70840",
                "long_title": "看不见的墙",
                "pub_time": 1443537120,
                "pv": 0,
                "release_date": "",
                "rights": {
                    "allow_demand": 0,
                    "allow_dm": 1,
                    "allow_download": 1,
                    "area_limit": 0
                },
                "share_copy": "《宇宙星路》第21话 看不见的墙",
                "share_url": "https://www.bilibili.com/bangumi/play/ep70840",
                "short_link": "https://b23.tv/ep70840",
                "skip": {
                    "ed": {
                        "end": 1385,
                        "start": 1314
                    },
                    "op": {
                        "end": 120,
                        "start": 30
                    }
                },
                "status": 2,
                "subtitle": "已观看23万次",
                "title": "21",
                "vid": "2aa87d2c43"
            },
            {
                "aid": 2976215,
                "badge": "",
                "badge_info": {
                    "bg_color": "#FB7299",
                    "bg_color_night": "#BB5B76",
                    "text": ""
                },
                "badge_type": 0,
                "bvid": "BV1os41117PM",
                "cid": 4662713,
                "cover": "http://i0.hdslb.com/bfs/bangumi/374a75794162ac9e1dee43d5b22700c94d37df79.jpg",
                "dimension": {
                    "height": 0,
                    "rotate": 0,
                    "width": 0
                },
                "duration": 1417292,
                "from": "bangumi",
                "id": 70841,
                "is_view_hide": false,
                "link": "https://www.bilibili.com/bangumi/play/ep70841",
                "long_title": "各自的道路",
                "pub_time": 1443537120,
                "pv": 0,
                "release_date": "",
                "rights": {
                    "allow_demand": 0,
                    "allow_dm": 1,
                    "allow_download": 1,
                    "area_limit": 0
                },
                "share_copy": "《宇宙星路》第22话 各自的道路",
                "share_url": "https://www.bilibili.com/bangumi/play/ep70841",
                "short_link": "https://b23.tv/ep70841",
                "skip": {
                    "ed": {
                        "end": 1385,
                        "start": 1314
                    },
                    "op": {
                        "end": 120,
                        "start": 30
                    }
                },
                "status": 2,
                "subtitle": "已观看23万次",
                "title": "22",
                "vid": "a6b20fbd58"
            },
            {
                "aid": 2976215,
                "badge": "",
                "badge_info": {
                    "bg_color": "#FB7299",
                    "bg_color_night": "#BB5B76",
                    "text": ""
                },
                "badge_type": 0,
                "bvid": "BV1os41117PM",
                "cid": 4676357,
                "cover": "http://i0.hdslb.com/bfs/bangumi/374a75794162ac9e1dee43d5b22700c94d37df79.jpg",
                "dimension": {
                    "height": 0,
                    "rotate": 0,
                    "width": 0
                },
                "duration": 1417440,
                "from": "bangumi",
                "id": 85788,
                "is_view_hide": false,
                "link": "https://www.bilibili.com/bangumi/play/ep85788",
                "long_title": "所以你在",
                "pub_time": 1459824900,
                "pv": 0,
                "release_date": "",
                "rights": {
                    "allow_demand": 0,
                    "allow_dm": 1,
                    "allow_download": 1,
                    "area_limit": 0
                },
                "share_copy": "《宇宙星路》第23话 所以你在",
                "share_url": "https://www.bilibili.com/bangumi/play/ep85788",
                "short_link": "https://b23.tv/ep85788",
                "skip": {
                    "ed": {
                        "end": 1385,
                        "start": 1314
                    },
                    "op": {
                        "end": 120,
                        "start": 30
                    }
                },
                "status": 2,
                "subtitle": "已观看23万次",
                "title": "23",
                "vid": "70b674c45b"
            },
            {
                "aid": 2976215,
                "badge": "",
                "badge_info": {
                    "bg_color": "#FB7299",
                    "bg_color_night": "#BB5B76",
                    "text": ""
                },
                "badge_type": 0,
                "bvid": "BV1os41117PM",
                "cid": 4662715,
                "cover": "http://i0.hdslb.com/bfs/bangumi/374a75794162ac9e1dee43d5b22700c94d37df79.jpg",
                "dimension": {
                    "height": 0,
                    "rotate": 0,
                    "width": 0
                },
                "duration": 1417945,
                "from": "bangumi",
                "id": 70843,
                "is_view_hide": false,
                "link": "https://www.bilibili.com/bangumi/play/ep70843",
                "long_title": "再次的黑暗",
                "pub_time": 1443537120,
                "pv": 0,
                "release_date": "",
                "rights": {
                    "allow_demand": 0,
                    "allow_dm": 1,
                    "allow_download": 1,
                    "area_limit": 0
                },
                "share_copy": "《宇宙星路》第24话 再次的黑暗",
                "share_url": "https://www.bilibili.com/bangumi/play/ep70843",
                "short_link": "https://b23.tv/ep70843",
                "skip": {
                    "ed": {
                        "end": 1385,
                        "start": 1314
                    },
                    "op": {
                        "end": 120,
                        "start": 30
                    }
                },
                "status": 2,
                "subtitle": "已观看23万次",
                "title": "24",
                "vid": "aac2dad489"
            },
            {
                "aid": 2976215,
                "badge": "",
                "badge_info": {
                    "bg_color": "#FB7299",
                    "bg_color_night": "#BB5B76",
                    "text": ""
                },
                "badge_type": 0,
                "bvid": "BV1os41117PM",
                "cid": 4700153,
                "cover": "http://i0.hdslb.com/bfs/bangumi/374a75794162ac9e1dee43d5b22700c94d37df79.jpg",
                "dimension": {
                    "height": 0,
                    "rotate": 0,
                    "width": 0
                },
                "duration": 1417167,
                "from": "bangumi",
                "id": 70738,
                "is_view_hide": false,
                "link": "https://www.bilibili.com/bangumi/play/ep70738",
                "long_title": "再见",
                "pub_time": 1443537120,
                "pv": 0,
                "release_date": "",
                "rights": {
                    "allow_demand": 0,
                    "allow_dm": 1,
                    "allow_download": 1,
                    "area_limit": 0
                },
                "share_copy": "《宇宙星路》第25话 再见",
                "share_url": "https://www.bilibili.com/bangumi/play/ep70738",
                "short_link": "https://b23.tv/ep70738",
                "skip": {
                    "ed": {
                        "end": 1385,
                        "start": 1314
                    },
                    "op": {
                        "end": 120,
                        "start": 30
                    }
                },
                "status": 2,
                "subtitle": "已观看23万次",
                "title": "25",
                "vid": "8669ea53c3"
            },
            {
                "aid": 2976215,
                "badge": "",
                "badge_info": {
                    "bg_color": "#FB7299",
                    "bg_color_night": "#BB5B76",
                    "text": ""
                },
                "badge_type": 0,
                "bvid": "BV1os41117PM",
                "cid": 4662717,
                "cover": "http://i0.hdslb.com/bfs/bangumi/374a75794162ac9e1dee43d5b22700c94d37df79.jpg",
                "dimension": {
                    "height": 360,
                    "rotate": 0,
                    "width": 480
                },
                "duration": 1386000,
                "from": "bangumi",
                "id": 70845,
                "is_view_hide": false,
                "link": "https://www.bilibili.com/bangumi/play/ep70845",
                "long_title": "闪光的声音",
                "pub_time": 1443537166,
                "pv": 0,
                "release_date": "",
                "rights": {
                    "allow_demand": 0,
                    "allow_dm": 1,
                    "allow_download": 1,
                    "area_limit": 0
                },
                "share_copy": "《宇宙星路》第26话 闪光的声音",
                "share_url": "https://www.bilibili.com/bangumi/play/ep70845",
                "short_link": "https://b23.tv/ep70845",
                "skip": {
                    "ed": {
                        "end": 1386,
                        "start": 1314
                    },
                    "op": {
                        "end": 120,
                        "start": 30
                    }
                },
                "status": 2,
                "subtitle": "已观看23万次",
                "title": "26",
                "vid": "3019b01b0f"
            }
        ],
        "evaluate": "“这是距今189年前（西历2167年）所发生的事，当时水蛇座β星（Hydrusβ）发生超新星爆炸，即使距离它20光年的地球也受到很大的伤害。充满着瓦斯的绿色宇宙，这我所知道的宇宙的颜色。不过我很想看看，从前的人们从地球抬头望天所见的宇宙的颜色，所以我要去Stellvia。现在是西历2356年……”\n",
        "freya": {
            "bubble_desc": "",
            "bubble_show_cnt": 0,
            "icon_show": 1
        },
        "jp_title": "",
        "link": "http://www.bilibili.com/bangumi/media/md1985/",
        "media_id": 1985,
        "mode": 2,
        "new_ep": {
            "desc": "已完结, 全26话",
            "id": 70845,
            "is_new": 0,
            "title": "26"
        },
        "positive": {
            "id": 18971,
            "title": "正片"
        },
        "publish": {
            "is_finish": 1,
            "is_started": 1,
            "pub_time": "2003-04-02 00:00:00",
            "pub_time_show": "2003年04月02日00:00",
            "unknow_pub_date": 0,
            "weekday": 0
        },
        "rating": {
            "count": 130,
            "score": 9.6
        },
        "record": "",
        "rights": {
            "allow_bp": 0,
            "allow_bp_rank": 0,
            "allow_download": 0,
            "allow_review": 1,
            "area_limit": 316,
            "ban_area_show": 1,
            "can_watch": 1,
            "copyright": "ugc",
            "forbid_pre": 0,
            "freya_white": 0,
            "is_cover_show": 0,
            "is_preview": 0,
            "only_vip_download": 0,
            "resource": "",
            "watch_platform": 0
        },
        "season_id": 1985,
        "season_title": "宇宙星路",
        "seasons": [
            {
                "badge": "",
                "badge_info": {
                    "bg_color": "#FB7299",
                    "bg_color_night": "#BB5B76",
                    "text": ""
                },
                "badge_type": 0,
                "cover": "http://i0.hdslb.com/bfs/bangumi/3c8bae3be4814ad09a77e7dd79f4bd4d1e10a7cb.jpg",
                "horizontal_cover_1610": "",
                "horizontal_cover_169": "",
                "media_id": 1985,
                "new_ep": {
                    "cover": "http://i0.hdslb.com/bfs/bangumi/374a75794162ac9e1dee43d5b22700c94d37df79.jpg",
                    "id": 70845,
                    "index_show": "全26话"
                },
                "season_id": 1985,
                "season_title": "TV版",
                "season_type": 1,
                "stat": {
                    "favorites": 10712,
                    "series_follow": 10712,
                    "views": 230220
                }
            }
        ],
        "series": {
            "display_type": 0,
            "series_id": 1347,
            "series_title": "宇宙星路"
        },
        "share_copy": "《宇宙星路》",
        "share_sub_title": "",
        "share_url": "https://www.bilibili.com/bangumi/play/ss1985",
        "show": {
            "wide_screen": 0
        },
        "show_season_type": 1,
        "square_cover": "http://i0.hdslb.com/bfs/bangumi/83ca0af8d1d3fae3bb190e8f3a20af569bd148cb.jpg",
        "stat": {
            "coins": 435,
            "danmakus": 4312,
            "favorite": 164,
            "favorites": 10712,
            "likes": 371,
            "reply": 288,
            "share": 81,
            "views": 230220
        },
        "status": 2,
        "subtitle": "已观看23万次",
        "title": "宇宙星路",
        "total": 26,
        "type": 1,
        "user_status": {
            "area_limit": 0,
            "ban_area_show": 0,
            "follow": 0,
            "follow_status": 0,
            "login": 0,
            "pay": 0,
            "pay_pack_paid": 0,
            "sponsor": 0
        }
    }
}